chainfl/__init__.py
chainfl/agent/__init__.py
chainfl/agent/communicator.py
chainfl/agent/local_trainer.py
chainfl/agent/model_hasher.py
chainfl/agent/signer.py
chainfl/blockchain/__init__.py
chainfl/blockchain/block.py
chainfl/blockchain/blockchain_sim.py
chainfl/blockchain/consensus.py
chainfl/blockchain/explorer.py
chainfl/blockchain/validator.py
chainfl/coordinator/__init__.py
chainfl/coordinator/aggregator.py
chainfl/coordinator/integrity_checker.py
chainfl/coordinator/publisher.py
chainfl/simulator/__init__.py
chainfl/simulator/logger.py
chainfl/simulator/metrics.py
chainfl/simulator/scheduler.py
chainfl/simulator/simulation_runner.py
chainfl/utils/__init__.py
chainfl/utils/config_loader.py
chainfl/utils/crypto.py
chainfl-0.1.0.dist-info/LICENSE
chainfl-0.1.0.dist-info/METADATA
chainfl-0.1.0.dist-info/WHEEL
chainfl-0.1.0.dist-info/RECORD
